{"cameraMode":{"drawMode":0,"name":"Shaded","section":"Shading Mode"},"sceneLighting":true,"audioPlay":false,"sceneViewState":{"m_AlwaysRefresh":false,"showFog":true,"showSkybox":true,"showFlares":true,"showImageEffects":true,"showParticleSystems":true,"showVisualEffectGraphs":true,"m_FxEnabled":true},"in2DMode":false,"pivot":{"x":126.52559661865235,"y":-59.08784484863281,"z":109.24887084960938},"rotation":{"x":-0.23602250218391419,"y":-0.2995727062225342,"z":0.07675191760063172,"w":-0.9212263822555542},"size":99.58580780029297,"orthographic":false}